LICENSE
MANIFEST.in
README.rst
setup.py
doc/Makefile
doc/html/.buildinfo
doc/html/.nojekyll
doc/html/download.html
doc/html/exampleshtml.html
doc/html/genindex.html
doc/html/index.html
doc/html/objects.inv
doc/html/reference.html
doc/html/revision_history.html
doc/html/search.html
doc/html/searchindex.js
doc/html/tutorial.html
doc/html/_images/jointmarginal.png
doc/html/_sources/bibliography.rst.txt
doc/html/_sources/download.rst.txt
doc/html/_sources/examples.rst.txt
doc/html/_sources/exampleshtml.rst.txt
doc/html/_sources/index.rst.txt
doc/html/_sources/indexlatex.rst.txt
doc/html/_sources/introduction.rst.txt
doc/html/_sources/reference.rst.txt
doc/html/_sources/revision_history.rst.txt
doc/html/_sources/tutorial.rst.txt
doc/html/_static/ajax-loader.gif
doc/html/_static/basic.css
doc/html/_static/comment-bright.png
doc/html/_static/comment-close.png
doc/html/_static/comment.png
doc/html/_static/doctools.js
doc/html/_static/down-pressed.png
doc/html/_static/down.png
doc/html/_static/file.png
doc/html/_static/jquery-3.1.0.js
doc/html/_static/jquery.js
doc/html/_static/minus.png
doc/html/_static/plus.png
doc/html/_static/pygments.css
doc/html/_static/searchtools.js
doc/html/_static/underscore-1.3.1.js
doc/html/_static/underscore.js
doc/html/_static/up-pressed.png
doc/html/_static/up.png
doc/html/_static/websupport.js
doc/html/_static/css/badge_only.css
doc/html/_static/css/theme.css
doc/html/_static/fonts/Inconsolata-Bold.ttf
doc/html/_static/fonts/Inconsolata-Regular.ttf
doc/html/_static/fonts/Lato-Bold.ttf
doc/html/_static/fonts/Lato-Regular.ttf
doc/html/_static/fonts/RobotoSlab-Bold.ttf
doc/html/_static/fonts/RobotoSlab-Regular.ttf
doc/html/_static/fonts/fontawesome-webfont.eot
doc/html/_static/fonts/fontawesome-webfont.svg
doc/html/_static/fonts/fontawesome-webfont.ttf
doc/html/_static/fonts/fontawesome-webfont.woff
doc/html/_static/js/modernizr.min.js
doc/html/_static/js/theme.js
doc/source/.nojekyll
doc/source/bibliography.rst
doc/source/conf.py
ncpol2sdpa.egg-info/PKG-INFO
ncpol2sdpa.egg-info/SOURCES.txt
ncpol2sdpa.egg-info/dependency_links.txt
ncpol2sdpa.egg-info/requires.txt
ncpol2sdpa.egg-info/top_level.txt
