Metadata-Version: 1.1
Name: ncpol2sdpa
Version: 1.12.2
Summary: Solve global polynomial optimization problems of either                 commutative variables or noncommutative operators through                 a semidefinite programming (SDP) relaxation
Home-page: http://ncpol2sdpa.readthedocs.io/
Author: Peter Wittek
Author-email: peterwittek@users.noreply.github.com
License: LICENSE
Keywords: sdp,semidefinite programming,relaxation,polynomial optimization problem,noncommuting variable,sdpa
Platform: UNKNOWN
Classifier: License :: OSI Approved :: GNU General Public License v3 (GPLv3)
Classifier: Operating System :: OS Independent
Classifier: Development Status :: 4 - Beta
Classifier: Topic :: Scientific/Engineering :: Mathematics
Classifier: Topic :: Scientific/Engineering :: Physics
Classifier: Intended Audience :: Science/Research
Classifier: Programming Language :: Python
